edit_distance.cpython-39-darwin.so
lcs.cpython-39-darwin.so
fuzzy_lightning/__init__.py
fuzzy_lightning/fuzzy_match.py
fuzzy_lightning/tokenize.py
fuzzy_lightning/cpp/array.h
fuzzy_lightning/cpp/edit_distance.cpp
fuzzy_lightning/cpp/lcs.cpp
fuzzy_lightning-0.1.5.dist-info/LICENSE
fuzzy_lightning-0.1.5.dist-info/METADATA
fuzzy_lightning-0.1.5.dist-info/WHEEL
fuzzy_lightning-0.1.5.dist-info/top_level.txt
fuzzy_lightning-0.1.5.dist-info/RECORD
