Metadata-Version: 2.1
Name: fuzzy-lightning
Version: 0.1.5
Summary: Perform fast fuzzy string lookups.
Home-page: https://github.com/tomukmatthews/fuzzy-lightning
Author: Tom Matthews
Author-email: tomukmatthews@gmail.com
Maintainer: Tom Matthews
Maintainer-email: tomukmatthews@gmail.com
Requires-Python: >=3.8.1,<4.0.0
License-File: LICENSE
Requires-Dist: pybind11 (>=2.6.0)
Requires-Dist: scikit-learn (>=1.0.2)
Requires-Dist: scipy (>=1.7.0)
Requires-Dist: sparse-dot-topn (>=0.3.1)
